MANIFEST.in
README.md
requirements.txt
setup.py
cys2n/__init__.py
cys2n/cys2n.c
cys2n/cys2n.pxd
cys2n/cys2n.pyx
cys2n.egg-info/PKG-INFO
cys2n.egg-info/SOURCES.txt
cys2n.egg-info/dependency_links.txt
cys2n.egg-info/top_level.txt