Metadata-Version: 1.1
Name: cys2n
Version: 0.1.1
Summary: Cython wrapper for Amazon s2n
Home-page: http://github.com/samrushing/cys2n
Author: Sam Rushing
Author-email: gitsam@rushing.nightmare.com
License: BSD
Download-URL: https://pypi.python.org/pypi?name=cys2n
Platform: UNKNOWN
